setup.py
python/ups/__init__.py
python/ups/commands.py
python/ups/depend.py
python/ups/dot.py
python/ups/manifest.py
python/ups/mirror.py
python/ups/objects.py
python/ups/packages.py
python/ups/products.py
python/ups/repos.py
python/ups/survey.py
python/ups/tarballs.py
python/ups/tofix.py
python/ups/tree.py
python/ups/urman.py
python/ups/util.py
python/ups_utils.egg-info/PKG-INFO
python/ups_utils.egg-info/SOURCES.txt
python/ups_utils.egg-info/dependency_links.txt
python/ups_utils.egg-info/entry_points.txt
python/ups_utils.egg-info/requires.txt
python/ups_utils.egg-info/top_level.txt