Metadata-Version: 1.0
Name: ups-utils
Version: 0.3
Summary: UPS Utilities
Home-page: http://github.com/brettviren/python-ups-utils
Author: Brett Viren
Author-email: brett.viren@gmail.com
License: GPLv2
Platform: UNKNOWN
